Workbook

Sheet Instructions
A1: BES Vendor Demonstration and Evaluation Scorecard
A2: INTERNAL – DRAFT v0.1 – do not share with vendors. Yellow cells are for BES to complete.
A4: Purpose | B4: Compare vendors fairly and consistently for the exploratory assessment of an AI-assisted customer service and CRM system with WhatsApp Business. No vendor has been selected and no project is approved.
A5: Sheets | B5: Vendors (names and weights) → Gates (pass/fail) → Demo sheets (live demonstration) → Cost (price comparison) → Scoring (weighted criteria) → Summary (results) → Follow-up (missing information).
A6: Step 1 – Mandatory gates | B6: Before relying on any score, complete the Gates sheet. Any Fail excludes the proposal (unless management documents an exception). Pending means evidence is outstanding – follow up; do not assume a pass.
A7: Step 2 – Scoring scale | B7: 5 = Excellent, exceeds requirement, evidenced · 4 = Good · 3 = Meets requirement · 2 = Partly meets / material gaps · 1 = Poor · 0 = Information was provided and shows the requirement is NOT met. **Leave blank when information is missing** and log it on the Follow-up sheet.
A8: Missing information | B8: A blank score is NOT zero. Blank criteria are excluded from the category average, and the Summary shows Completeness (scored criteria ÷ all criteria). A weighted score is calculated on available information only; vendors with completeness below the threshold on the Vendors sheet (default 80%) are flagged 'Insufficient information' and are not ranked until follow-up is done.
A9: Evidence rule | B9: Score on documents and live demonstration, not on claims. Record the evidence source in the Notes column. Where a claim could not be verified, score conservatively and log a follow-up.
A10: Weights | B10: Provisional weights (25/20/20/20/10/5) are on the Vendors sheet. Management may change them; they must total 100%. Do not change weights after seeing results.
A11: Cost scoring | B11: The Cost sheet scores price by ratio (lowest comparable 3-year cost ÷ vendor's cost × 5) only when quotes cover the same scope. If scopes differ, normalise or override manually and explain in Notes. Cost is scored alongside, not instead of, value.
A12: Scorers | B12: Use at least two scorers; record each scorer's initials; resolve differences >1 point by discussion and record the agreed score.
A13: Limits | B13: Scores support, not replace, management judgement, legal review and reference checks. Do not rank vendors on incomplete information.

Sheet Vendors
A1: Vendors and weights
A3: # | B3: Vendor name (edit) | C3: Contact / notes
A4: 1 | B4: TechCom Africa
A5: 2 | B5: Vendor B
A6: 3 | B6: Vendor C
A7: 4 | B7: Vendor D
A10: Category | B10: Provisional weight (editable) | C10: Comment
A11: Functional capability | B11: 0.25 | C11: Provisional – management to confirm
A12: Implementation timeline and delivery | B12: 0.2 | C12: Provisional – management to confirm
A13: Total cost and value | B13: 0.2 | C13: Provisional – management to confirm
A14: Security, ownership, and data protection | B14: 0.2 | C14: Provisional – management to confirm
A15: Relevant experience and references | B15: 0.1 | C15: Provisional – management to confirm
A16: Support and operational suitability | B16: 0.05 | C16: Provisional – management to confirm
A17: Total (must equal 100%) | B17: =SUM(B11:B16) | C17: =IF(ROUND(B17,4)=1,"OK","Weights must total 100%")
A19: Minimum completeness to rank a vendor | B19: 0.8 | C19: Below this, vendor is flagged 'Insufficient information' and not ranked

Sheet Gates
A1: Mandatory pass / fail checks
A2: Fail on any gate = proposal excluded. Pending = evidence outstanding (follow up). Blank counts as Pending.
A4: ID | B4: Mandatory check | C4: What counts as evidence | D4: =Vendors!$B$4 | E4: =Vendors!$B$5 | F4: =Vendors!$B$6 | G4: =Vendors!$B$7
A5: G1 | B5: Official WhatsApp Business Platform integration; WABA/number/Meta portfolio registered to BES with BES admin control | C5: Written route statement; WABA ownership screenshots; partner status verified with Meta or in BES's Meta Business Manager
A6: G2 | B6: BES ownership of data, content, knowledge base and configuration; BES holds super-admin rights; no vendor-only credentials | C6: Contract/ownership statement; account list showing owners
A7: G3 | B7: Role-based access control and MFA (at least admins), including restriction by team/department as BES requires | C7: Live demo; role matrix; MFA demonstration
A8: G4 | B8: Data portability: full export in open formats; documented exit and deletion process | C8: Sample export; exit clause
A9: G5 | B9: Security baseline: encryption in transit and at rest, audit logs, backups with restore capability, incident notification | C9: Security policy/whitepaper; certificates (scope+date checked); pen-test summary; backup policy
A10: G6 | B10: Disclosure of hosting locations, AI providers and sub-processors; no training of shared/public AI models on BES data | C10: Sub-processor list; AI provider terms; written no-training commitment
A11: G7 | B11: Willing to sign a data-processing agreement consistent with NDPA 2023 before real client data is processed | C11: Draft DPA; cross-border transfer mechanism
A12: G8 | B12: Clearly defined deliverables, milestones, acceptance criteria and itemised pricing for the proposed scope | C12: Completed Parts D and E of quotation template
B13: OVERALL GATE RESULT | D13: =IF(COUNTIF(D5:D12,"Fail")>0,"FAIL",IF(COUNTIF(D5:D12,"Pass")=8,"PASS","HOLD – follow up")) | E13: =IF(COUNTIF(E5:E12,"Fail")>0,"FAIL",IF(COUNTIF(E5:E12,"Pass")=8,"PASS","HOLD – follow up")) | F13: =IF(COUNTIF(F5:F12,"Fail")>0,"FAIL",IF(COUNTIF(F5:F12,"Pass")=8,"PASS","HOLD – follow up")) | G13: =IF(COUNTIF(G5:G12,"Fail")>0,"FAIL",IF(COUNTIF(G5:G12,"Pass")=8,"PASS","HOLD – follow up"))
B15: Notes on any Fail/Pending (evidence, date requested, owner):

Sheet Demo - Vendor 1
A1: Live demonstration checklist
A2: ="Vendor: "&Vendors!$B$4
A4: # | B4: Demonstration item | C4: What to see | D4: Pass standard | E4: Availability (Now / Configuration / Development / Not available / Not shown) | F4: Rating 0–5 (blank if not shown) | G4: Cost to close gap (₦) if Configuration/Development | H4: Evidence / notes | I4: Follow-up needed?
A5: 1 | B5: Incoming WhatsApp enquiry | C5: Message sent to test number appears in inbox with time, number and history | D5: Arrives on official integration; no manual step
A6: 2 | B6: AI-generated response | C6: Reply uses only approved content; discloses automation; unknown and trap questions handled safely | D6: Correct answer; safe refusal/handover on unknown; source visible
A7: 3 | B7: Lead creation in CRM | C7: Record created automatically with captured fields; linked conversation; duplicate check | D7: No manual entry; fields correct
A8: 4 | B8: Staff assignment | C8: Rule-based and manual assignment; unassigned queue | D8: Correct owner; reassignment logged
A9: 5 | B9: Personalised document checklist | C9: Different categories produce different approved checklists; BES admin can edit templates | D9: Correct lists; edit without vendor
A10: 6 | B10: Document-status tracking | C10: Document received against checklist item; accept/reject; outstanding view | D10: Accurate status; access controlled
A11: 7 | B11: Follow-up scheduling | C11: Reminder sequence; stop on reply; opt-out; template/24-hour window handling | D11: Runs as configured; compliant
A12: 8 | B12: Human handover | C12: Triggers: ask for person, complaint, low confidence; AI stops; staff notified | D12: Correct trigger, notice and AI pause
A13: 9 | B13: Management reporting | C13: Dashboard of enquiries, response time, stages, overdue, documents; metric definitions | D13: Figures reconcile with test data
A14: 10 | B14: Role-based access | C14: Two roles see different data/actions; MFA shown | D14: Restrictions enforced
A15: 11 | B15: Audit history | C15: Log of the demo actions incl. config changes and exports | D15: Who/what/when accurate; not editable
A16: 12 | B16: Data export | C16: Export of contacts, conversations, documents in open formats | D16: Complete; usable
B18: Average demonstration rating (rated items only) | F18: =IF(COUNT(F5:F16)=0,"",AVERAGE(F5:F16))
B19: Items rated ÷ 12 (demo completeness) | F19: =COUNT(F5:F16)/12
B20: Items needing configuration / development | F20: =COUNTIF(E5:E16,"Configuration")&" / "&COUNTIF(E5:E16,"Development")

Sheet Demo - Vendor 2
A1: Live demonstration checklist
A2: ="Vendor: "&Vendors!$B$5
A4: # | B4: Demonstration item | C4: What to see | D4: Pass standard | E4: Availability (Now / Configuration / Development / Not available / Not shown) | F4: Rating 0–5 (blank if not shown) | G4: Cost to close gap (₦) if Configuration/Development | H4: Evidence / notes | I4: Follow-up needed?
A5: 1 | B5: Incoming WhatsApp enquiry | C5: Message sent to test number appears in inbox with time, number and history | D5: Arrives on official integration; no manual step
A6: 2 | B6: AI-generated response | C6: Reply uses only approved content; discloses automation; unknown and trap questions handled safely | D6: Correct answer; safe refusal/handover on unknown; source visible
A7: 3 | B7: Lead creation in CRM | C7: Record created automatically with captured fields; linked conversation; duplicate check | D7: No manual entry; fields correct
A8: 4 | B8: Staff assignment | C8: Rule-based and manual assignment; unassigned queue | D8: Correct owner; reassignment logged
A9: 5 | B9: Personalised document checklist | C9: Different categories produce different approved checklists; BES admin can edit templates | D9: Correct lists; edit without vendor
A10: 6 | B10: Document-status tracking | C10: Document received against checklist item; accept/reject; outstanding view | D10: Accurate status; access controlled
A11: 7 | B11: Follow-up scheduling | C11: Reminder sequence; stop on reply; opt-out; template/24-hour window handling | D11: Runs as configured; compliant
A12: 8 | B12: Human handover | C12: Triggers: ask for person, complaint, low confidence; AI stops; staff notified | D12: Correct trigger, notice and AI pause
A13: 9 | B13: Management reporting | C13: Dashboard of enquiries, response time, stages, overdue, documents; metric definitions | D13: Figures reconcile with test data
A14: 10 | B14: Role-based access | C14: Two roles see different data/actions; MFA shown | D14: Restrictions enforced
A15: 11 | B15: Audit history | C15: Log of the demo actions incl. config changes and exports | D15: Who/what/when accurate; not editable
A16: 12 | B16: Data export | C16: Export of contacts, conversations, documents in open formats | D16: Complete; usable
B18: Average demonstration rating (rated items only) | F18: =IF(COUNT(F5:F16)=0,"",AVERAGE(F5:F16))
B19: Items rated ÷ 12 (demo completeness) | F19: =COUNT(F5:F16)/12
B20: Items needing configuration / development | F20: =COUNTIF(E5:E16,"Configuration")&" / "&COUNTIF(E5:E16,"Development")

Sheet Cost
A1: Price comparison (from vendors' Part E / pricing workbook)
A2: Enter like-for-like totals in ₦ for the same scope and Base scenario. Taxes treatment must be consistent.
A4: Item | B4: =Vendors!$B$4 | C4: =Vendors!$B$5 | D4: =Vendors!$B$6 | E4: =Vendors!$B$7
A5: First-year total cost (₦) – Base scenario
A6: Year 2 recurring cost (₦)
A7: Year 3 recurring cost (₦)
A8: 3-year total cost of ownership (₦) | B8: =IF(COUNT(B5:B7)=3,SUM(B5:B7),"") | C8: =IF(COUNT(C5:C7)=3,SUM(C5:C7),"") | D8: =IF(COUNT(D5:D7)=3,SUM(D5:D7),"") | E8: =IF(COUNT(E5:E7)=3,SUM(E5:E7),"")
A9: Price score (0–5): lowest ÷ vendor × 5 | B9: =IF(B8="","",IF(MIN($B$8:$E$8)<=0,"",ROUND(MIN($B$8:$E$8)/B8*5,1))) | C9: =IF(C8="","",IF(MIN($B$8:$E$8)<=0,"",ROUND(MIN($B$8:$E$8)/C8*5,1))) | D9: =IF(D8="","",IF(MIN($B$8:$E$8)<=0,"",ROUND(MIN($B$8:$E$8)/D8*5,1))) | E9: =IF(E8="","",IF(MIN($B$8:$E$8)<=0,"",ROUND(MIN($B$8:$E$8)/E8*5,1)))
A10: Priced in US$ or other foreign currency? (Y/N)
A11: Pricing scope comparable with other quotes? (Y/N)
A12: Within first-year budget? (only if budget entered) | B12: =IF(OR($B$14="",B5=""),"",IF(B5<=$B$14,"Yes","No")) | C12: =IF(OR($B$14="",C5=""),"",IF(C5<=$B$14,"Yes","No")) | D12: =IF(OR($B$14="",D5=""),"",IF(D5<=$B$14,"Yes","No")) | E12: =IF(OR($B$14="",E5=""),"",IF(E5<=$B$14,"Yes","No"))
A13: BES approved budget – management to complete (₦). INTERNAL – do not share
A14: First-year budget (₦)
A15: Annual recurring budget (₦)
A17: Notes: price score uses MIN across vendors that have entered all three years. If scopes are not comparable, override the 'Price' criterion on the Scoring sheet manually and explain. Foreign-currency pricing: record the exchange rate and date used and consider a sensitivity check (e.g. ±20% on the exchange rate).

Sheet Scoring
A1: Weighted criteria scoring (0–5; leave blank if information is missing)
A2: Equal weight to each criterion within its category. Green cells are linked from other sheets; you may overwrite with a documented reason.
A4: Category | B4: Criterion | C4: What a 3 (meets) looks like | D4: =Vendors!$B$4 | E4: =Vendors!$B$5 | F4: =Vendors!$B$6 | G4: =Vendors!$B$7 | H4: Notes / evidence / scorer initials
A5: Functional capability | B5: Coverage of Essential requirements R1–R18 for Phase 1 (via RFQ matrix) | C5: All Phase 1 Essentials available now or via priced configuration
A6: Functional capability | B6: AI grounding, safeguards and handover | C6: Answers limited to approved content; safe fallback; handover triggers work
A7: Functional capability | B7: Document checklists, tracking and follow-ups | C7: Category-based checklists, status tracking and reminders available (Phase 2 acceptable)
A8: Functional capability | B8: CRM configurability, reporting and role fit | C8: BES can configure fields/stages/reports/roles without developers
A9: Functional capability | B9: Live demonstration performance (from Demo sheet) | C9: Most items shown live, working as specified | D9: ='Demo - Vendor 1'!F18 | E9: ='Demo - Vendor 2'!F18
A10: Implementation timeline and delivery | B10: Realistic expected timeline; clock-start clearly defined | C10: Defined start event; expected dates credible; risks stated
A11: Implementation timeline and delivery | B11: Quality of plan, milestones, deliverables, acceptance criteria | C11: Clear and testable
A12: Implementation timeline and delivery | B12: Dependencies and assumptions transparent and reasonable | C12: Stated; reasonable demands on BES
A13: Implementation timeline and delivery | B13: Delivery team, capacity, change and delay handling | C13: Named PM/lead; documented procedure
A14: Total cost and value | B14: Three-year cost (price score from Cost sheet) | C14: Price-ratio score | D14: =Cost!B9 | E14: =Cost!C9 | F14: =Cost!D9 | G14: =Cost!E9
A15: Total cost and value | B15: Pricing completeness and transparency (all 12 lines, usage, FX) | C15: All lines priced; assumptions shown
A16: Total cost and value | B16: Scalability of pricing (extra users, volume) and lock-in terms | C16: Published rates; reasonable terms
A17: Total cost and value | B17: Value for money relative to functionality delivered | C17: Fair for what is delivered
A18: Security, ownership, and data protection | B18: Data ownership, admin control and WhatsApp account ownership | C18: BES-owned accounts with BES super-admin
A19: Security, ownership, and data protection | B19: Hosting, sub-processors and AI provider data use | C19: Fully disclosed; no training on BES data
A20: Security, ownership, and data protection | B20: Security controls and evidence (encryption, MFA, audit, backup, incidents) | C20: Evidence supplied and credible
A21: Security, ownership, and data protection | B21: NDPA readiness and contract terms (DPA, breach, retention, deletion) | C21: DPA offered; process described
A22: Security, ownership, and data protection | B22: Data portability and exit | C22: Full export; defined exit
A23: Relevant experience and references | B23: Relevant projects (WhatsApp + CRM + AI) | C23: At least one comparable project
A24: Relevant experience and references | B24: Nigerian / African market experience | C24: Present in market
A25: Relevant experience and references | B25: Reference check results | C25: Positive, relevant references
A26: Relevant experience and references | B26: Company credibility and stability | C26: Verifiable company and team
... A29: Support and operational suitability | B29: Ongoing maintenance, account management and roadmap | C29: Defined and fair

Sheet Summary
A1: Results summary
A2: Weighted score is out of 100 and uses only criteria that have been scored. Read it together with completeness and gate status.
A4: Measure | B4: =Vendors!$B$4 | C4: =Vendors!$B$5 | D4: =Vendors!$B$6 | E4: =Vendors!$B$7
A5: Mandatory gate result | B5: =Gates!D13 | C5: =Gates!E13 | D5: =Gates!F13 | E5: =Gates!G13
A6: Completeness (criteria scored ÷ total) | B6: =COUNT(Scoring!D5:D29)/25 | C6: =COUNT(Scoring!E5:E29)/25 | D6: =COUNT(Scoring!F5:F29)/25 | E6: =COUNT(Scoring!G5:G29)/25
A7: ="Avg 0–5: "&Vendors!A11&" ("&TEXT(Vendors!B11,"0%")&")" | B7: =IF(COUNT(Scoring!D5:D9)=0,"",ROUND(AVERAGE(Scoring!D5:D9),2)) | C7: =IF(COUNT(Scoring!E5:E9)=0,"",ROUND(AVERAGE(Scoring!E5:E9),2)) | D7: =IF(COUNT(Scoring!F5:F9)=0,"",ROUND(AVERAGE(Scoring!F5:F9),2)) | E7: =IF(COUNT(Scoring!G5:G9)=0,"",ROUND(AVERAGE(Scoring!G5:G9),2))
A8: ="Avg 0–5: "&Vendors!A12&" ("&TEXT(Vendors!B12,"0%")&")" | B8: =IF(COUNT(Scoring!D10:D13)=0,"",ROUND(AVERAGE(Scoring!D10:D13),2)) | C8: =IF(COUNT(Scoring!E10:E13)=0,"",ROUND(AVERAGE(Scoring!E10:E13),2)) | D8: =IF(COUNT(Scoring!F10:F13)=0,"",ROUND(AVERAGE(Scoring!F10:F13),2)) | E8: =IF(COUNT(Scoring!G10:G13)=0,"",ROUND(AVERAGE(Scoring!G10:G13),2))
A9: ="Avg 0–5: "&Vendors!A13&" ("&TEXT(Vendors!B13,"0%")&")" | B9: =IF(COUNT(Scoring!D14:D17)=0,"",ROUND(AVERAGE(Scoring!D14:D17),2)) | C9: =IF(COUNT(Scoring!E14:E17)=0,"",ROUND(AVERAGE(Scoring!E14:E17),2)) | D9: =IF(COUNT(Scoring!F14:F17)=0,"",ROUND(AVERAGE(Scoring!F14:F17),2)) | E9: =IF(COUNT(Scoring!G14:G17)=0,"",ROUND(AVERAGE(Scoring!G14:G17),2))
A10: ="Avg 0–5: "&Vendors!A14&" ("&TEXT(Vendors!B14,"0%")&")" | B10: =IF(COUNT(Scoring!D18:D22)=0,"",ROUND(AVERAGE(Scoring!D18:D22),2)) | C10: =IF(COUNT(Scoring!E18:E22)=0,"",ROUND(AVERAGE(Scoring!E18:E22),2)) | D10: =IF(COUNT(Scoring!F18:F22)=0,"",ROUND(AVERAGE(Scoring!F18:F22),2)) | E10: =IF(COUNT(Scoring!G18:G22)=0,"",ROUND(AVERAGE(Scoring!G18:G22),2))
A11: ="Avg 0–5: "&Vendors!A15&" ("&TEXT(Vendors!B15,"0%")&")" | B11: =IF(COUNT(Scoring!D23:D26)=0,"",ROUND(AVERAGE(Scoring!D23:D26),2)) | C11: =IF(COUNT(Scoring!E23:E26)=0,"",ROUND(AVERAGE(Scoring!E23:E26),2)) | D11: =IF(COUNT(Scoring!F23:F26)=0,"",ROUND(AVERAGE(Scoring!F23:F26),2)) | E11: =IF(COUNT(Scoring!G23:G26)=0,"",ROUND(AVERAGE(Scoring!G23:G26),2))
A12: ="Avg 0–5: "&Vendors!A16&" ("&TEXT(Vendors!B16,"0%")&")" | B12: =IF(COUNT(Scoring!D27:D29)=0,"",ROUND(AVERAGE(Scoring!D27:D29),2)) | C12: =IF(COUNT(Scoring!E27:E29)=0,"",ROUND(AVERAGE(Scoring!E27:E29),2)) | D12: =IF(COUNT(Scoring!F27:F29)=0,"",ROUND(AVERAGE(Scoring!F27:F29),2)) | E12: =IF(COUNT(Scoring!G27:G29)=0,"",ROUND(AVERAGE(Scoring!G27:G29),2))
A13: Weighted score /100 (available information only) | B13: =IF((IF(B7="",0,Vendors!$B$11)+IF(B8="",0,Vendors!$B$12)+IF(B9="",0,Vendors!$B$13)+IF(B10="",0,Vendors!$B$14)+IF(B11="",0,Vendors!$B$15)+IF(B12="",0,Vendors!$B$16))=0,"",ROUND((IF(B7="",0,B7/5*Vendors!$B$11)+IF(B8="",0,B8/5*Vendors!$B$12)+IF(B9="",0,B9/5*Vendors!$B$13)+IF(B10="",0,B10/5*Vendors!$B$14)+IF(B11="",0,B11/5*Vendors!$B$15)+IF(B12="",0,B12/5*Vendors!$B$16))/(IF(B7="",0,Vendors!$B$11)+IF(B8="",0,Vendors!$B$12)+IF(B9="",0,Vendors!$B$13)+IF(B10="",0,Vendors!$B$14)+IF(B11="",0,Vendors!$B$15)+IF(B12="",0,Vendors!$B$16))*100,1)) | C13: =IF((IF(C7="",0,Vendors!$B$11)+IF(C8="",0,Vendors!$B$12)+IF(C9="",0,Vendors!$B$13)+IF(C10="",0,Vendors!$B$14)+IF(C11="",0,Vendors!$B$15)+IF(C12="",0,Vendors!$B$16))=0,"",ROUND((IF(C7="",0,C7/5*Vendors!$B$11)+IF(C8="",0,C8/5*Vendors!$B$12)+IF(C9="",0,C9/5*Vendors!$B$13)+IF(C10="",0,C10/5*Vendors!$B$14)+IF(C11="",0,C11/5*Vendors!$B$15)+IF(C12="",0,C12/5*Vendors!$B$16))/(IF(C7="",0,Vendors!$B$11)+IF(C8="",0,Vendors!$B$12)+IF(C9="",0,Vendors!$B$13)+IF(C10="",0,Vendors!$B$14)+IF(C11="",0,Vendors!$B$15)+IF(C12="",0,Vendors!$B$16))*100,1)) | D13: =IF((IF(D7="",0,Vendors!$B$11)+IF(D8="",0,Vendors!$B$12)+IF(D9="",0,Vendors!$B$13)+IF(D10="",0,Vendors!$B$14)+IF(D11="",0,Vendors!$B$15)+IF(D12="",0,Vendors!$B$16))=0,"",ROUND((IF(D7="",0,D7/5*Vendors!$B$11)+IF(D8="",0,D8/5*Vendors!$B$12)+IF(D9="",0,D9/5*Vendors!$B$13)+IF(D10="",0,D10/5*Vendors!$B$14)+IF(D11="",0,D11/5*Vendors!$B$15)+IF(D12="",0,D12/5*Vendors!$B$16))/(IF(D7="",0,Vendors!$B$11)+IF(D8="",0,Vendors!$B$12)+IF(D9="",0,Vendors!$B$13)+IF(D10="",0,Vendors!$B$14)+IF(D11="",0,Vendors!$B$15)+IF(D12="",0,Vendors!$B$16))*100,1)) | E13: =IF((IF(E7="",0,Vendors!$B$11)+IF(E8="",0,Vendors!$B$12)+IF(E9="",0,Vendors!$B$13)+IF(E10="",0,Vendors!$B$14)+IF(E11="",0,Vendors!$B$15)+IF(E12="",0,Vendors!$B$16))=0,"",ROUND((IF(E7="",0,E7/5*Vendors!$B$11)+IF(E8="",0,E8/5*Vendors!$B$12)+IF(E9="",0,E9/5*Vendors!$B$13)+IF(E10="",0,E10/5*Vendors!$B$14)+IF(E11="",0,E11/5*Vendors!$B$15)+IF(E12="",0,E12/5*Vendors!$B$16))/(IF(E7="",0,Vendors!$B$11)+IF(E8="",0,Vendors!$B$12)+IF(E9="",0,Vendors!$B$13)+IF(E10="",0,Vendors!$B$14)+IF(E11="",0,Vendors!$B$15)+IF(E12="",0,Vendors!$B$16))*100,1))
A14: Categories with no scores yet | B14: =COUNTBLANK(B7:B12) | C14: =COUNTBLANK(C7:C12) | D14: =COUNTBLANK(D7:D12) | E14: =COUNTBLANK(E7:E12)
A15: Status | B15: =IF(B5="FAIL","Excluded – failed mandatory gate",IF(B6<Vendors!$B$19,"Insufficient information – follow up before ranking",IF(B5<>"PASS","Gates pending – provisional only","Eligible for ranking"))) | C15: =IF(C5="FAIL","Excluded – failed mandatory gate",IF(C6<Vendors!$B$19,"Insufficient information – follow up before ranking",IF(C5<>"PASS","Gates pending – provisional only","Eligible for ranking"))) | D15: =IF(D5="FAIL","Excluded – failed mandatory gate",IF(D6<Vendors!$B$19,"Insufficient information – follow up before ranking",IF(D5<>"PASS","Gates pending – provisional only","Eligible for ranking"))) | E15: =IF(E5="FAIL","Excluded – failed mandatory gate",IF(E6<Vendors!$B$19,"Insufficient information – follow up before ranking",IF(E5<>"PASS","Gates pending – provisional only","Eligible for ranking")))
A16: Ranking score (eligible vendors only) | B16: =IF(B15="Eligible for ranking",B13,"") | C16: =IF(C15="Eligible for ranking",C13,"") | D16: =IF(D15="Eligible for ranking",D13,"") | E16: =IF(E15="Eligible for ranking",E13,"")
A17: Rank | B17: =IF(B16="","",RANK(B16,$B$16:$E$16)) | C17: =IF(C16="","",RANK(C16,$B$16:$E$16)) | D17: =IF(D16="","",RANK(D16,$B$16:$E$16)) | E17: =IF(E16="","",RANK(E16,$B$16:$E$16))
A19: Sensitivity check: reviewers should re-run with weights changed ±5 points on Cost and Functional to see whether the ranking is stable; if not, treat vendors as comparable and decide on risk, evidence and references.

Sheet Follow-up
A1: Missing information and follow-up log
A2: Log every blank score, Pending gate and unverified claim. Do not leave them as zero.
A4: # | B4: Vendor | C4: Criterion / gate | D4: Information or evidence needed | E4: Requested on | F4: Owner | G4: Due | H4: Status (Open / Received / Not provided) | I4: Outcome / effect on score
A5: 1
A6: 2
A7: 3
A8: 4
A9: 5
A10: 6
A11: 7
A12: 8
A13: 9
A14: 10
A15: 11
A16: 12
... A39: 35
